freakble/__init__.py
freakble/__main__.py
freakble/ble.py
freakble/cli.py
freakble/gui.py
freakble/repl.py
freakble-0.6.2.dist-info/WHEEL
freakble-0.6.2.dist-info/entry_points.txt
freakble-0.6.2.dist-info/LICENSE
freakble-0.6.2.dist-info/METADATA
freakble-0.6.2.dist-info/RECORD
