Metadata-Version: 2.1
Name: freakble
Version: 0.6.2
Summary: A simple tool to send messages into FreakWAN over Bluetooth low energy.
Home-page: https://github.com/eriol/freakble
License: BSD-3-Clause
Author: Daniele Tricoli
Author-email: eriol@mornie.org
Requires-Python: >=3.8,<4.0
Classifier: Development Status :: 3 - Alpha
Classifier: License :: OSI Approved :: BSD License
Classifier: Operating System :: MacOS :: MacOS X
Classifier: Operating System :: Microsoft :: Windows :: Windows 10
Classifier: Operating System :: POSIX :: Linux
Classifier: Programming Language :: Python :: 3
Classifier: Programming Language :: Python :: 3.8
Classifier: Programming Language :: Python :: 3.9
Classifier: Programming Language :: Python :: 3.10
Classifier: Programming Language :: Python :: 3.11
Classifier: Topic :: Communications
Provides-Extra: themes
Requires-Dist: anyio (>=3.6.2,<4.0.0)
Requires-Dist: asyncclick (>=8.1.3.4,<9.0.0.0)
Requires-Dist: bleak (>=0.19.5,<0.20.0)
Requires-Dist: prompt-toolkit (>=3.0.36,<4.0.0)
Requires-Dist: ttkthemes (>=3.2.2,<4.0.0) ; extra == "themes"
Project-URL: Repository, https://github.com/eriol/freakble
